{
	"typeId": "9",
	"categoryId": "1",
	"type": "FE 74 HDV",
	"maxPrice": "315000000",
	"minCsp": "5",
	"insurance": "CV",
	"isActive": "1",
	"isAddb": "0",
	"activeDate": "2017-06-01",
	"endDate": "2017-04-01",
	"refund1": "400000",
	"refund2": "1300000",
	"refund3": "2350000",
	"refund4": "3250000",
	"refund5": "0",
	"remarks": "FE 74 HDV Normal Paket",
	"a1": "3.900",
	"a2": "3.000",
	"a3": "2.800",
	"a4": "2.500",
	"a5": "2.300",
	"a6": "2.000",
	"a7": "1.600",
	"a8": "1.200",
	"b1": "5.500",
	"b2": "4.800",
	"b3": "4.600",
	"b4": "4.400",
	"b5": "4.300",
	"b6": "4.000",
	"b7": "3.800",
	"b8": "3.500",
	"c1": "6.100",
	"c2": "5.600",
	"c3": "5.500",
	"c4": "5.400",
	"c5": "5.300",
	"c6": "5.100",
	"c7": "4.900",
	"c8": "4.700",
	"d1": "7.600",
	"d2": "7.200",
	"d3": "7.100",
	"d4": "7.000",
	"d5": "6.900",
	"d6": "6.800",
	"d7": "6.700",
	"d8": "6.500",
	"e1": "0.000",
	"e2": "0.000",
	"e3": "0.000",
	"e4": "0.000",
	"e5": "0.000",
	"e6": "0.000",
	"e7": "0.000",
	"e8": "0.000"
}